Selestium/ChromeHandler.py
Selestium/FirefoxHandler.py
Selestium/__init__.py
Selestium/selestium.py
selestium-0.2.8.dist-info/LICENSE
selestium-0.2.8.dist-info/METADATA
selestium-0.2.8.dist-info/WHEEL
selestium-0.2.8.dist-info/top_level.txt
selestium-0.2.8.dist-info/RECORD
