Metadata-Version: 2.1
Name: selestium
Version: 0.2.8
Summary: A Python module for web scraping with Selenium and BeautifulSoup
Home-page: https://github.com/09u2h4n/selestium
Author: Oğuzhan Yılmaz
License: UNKNOWN
Platform: UNKNOWN
Requires-Python: >=3.8
License-File: LICENSE
Requires-Dist: beautifulsoup4
Requires-Dist: requests
Requires-Dist: selenium
